pydeepsar/__init__.py
pydeepsar/__main__.py
pydeepsar/cli.py
pydeepsar/io/__init__.py
pydeepsar/io/xr.py
pydeepsar/models/__init__.py
pydeepsar/models/coherene.py
pydeepsar/models/layers.py
pydeepsar/py.typed
pydeepsar/pydeepsar.py
pydeepsar/util/__init__.py
pydeepsar/util/callback.py
pydeepsar/util/plot.py
pydeepsar-1.0.3.dist-info/LICENSE
pydeepsar-1.0.3.dist-info/METADATA
pydeepsar-1.0.3.dist-info/WHEEL
pydeepsar-1.0.3.dist-info/RECORD
