Metadata-Version: 2.1
Name: pydeepsar
Version: 1.0.3
Summary: This Project aims to ...
License: GNU General Public License v3
Author: Islam Mansour
Author-email: is3mansour@gmail.com
Requires-Python: >=3.9.1,<3.12
Classifier: License :: Other/Proprietary License
Classifier: Programming Language :: Python :: 3
Classifier: Programming Language :: Python :: 3.10
Classifier: Programming Language :: Python :: 3.11
Requires-Dist: netcdf4 (>=1.6.5,<2.0.0)
Requires-Dist: rioxarray (<0.15.1)
Requires-Dist: scikit-learn (>=1.4.1.post1,<2.0.0)
Requires-Dist: scipy (>=1.11.3)
Requires-Dist: seaborn (>=0.13.2,<0.14.0)
Requires-Dist: tensorflow (>=2.14,<=2.17.0)
Requires-Dist: tf-keras (>=2.16,<3.0)
